flask_softdeletes/__init__.py
flask_softdeletes/model.py
flask_softdeletes/query.py
Flask_SoftDeletes-1.0.2.dist-info/METADATA
Flask_SoftDeletes-1.0.2.dist-info/WHEEL
Flask_SoftDeletes-1.0.2.dist-info/top_level.txt
Flask_SoftDeletes-1.0.2.dist-info/RECORD
