Metadata-Version: 2.1
Name: Flask-SoftDeletes
Version: 1.0.2
Summary: 基于flask-sqlalchemy的软删除实现
Home-page: https://github.com/kanhebei/flask-softdeletes
Author: renjianguo
Author-email: renjianguo@kanhebei.cn
License: MIT
Platform: any
Classifier: Environment :: Web Environment
Classifier: Intended Audience :: Developers
Classifier: License :: OSI Approved :: BSD License
Classifier: Operating System :: OS Independent
Classifier: Programming Language :: Python
Classifier: Topic :: Internet :: WWW/HTTP :: Dynamic Content
Classifier: Topic :: Software Development :: Libraries :: Python Modules
Requires-Dist: Flask (>=1.1.2)
Requires-Dist: Flask-SQLAlchemy (>=2.4.4)
